qtfaststart2/__init__.py
qtfaststart2/__main__.py
qtfaststart2/command.py
qtfaststart2/exceptions.py
qtfaststart2/processor.py
qtfaststart2-2.1.1.data/scripts/qtfaststart2
qtfaststart2-2.1.1.dist-info/LICENSE.md
qtfaststart2-2.1.1.dist-info/METADATA
qtfaststart2-2.1.1.dist-info/WHEEL
qtfaststart2-2.1.1.dist-info/top_level.txt
qtfaststart2-2.1.1.dist-info/RECORD
